[{"date":"2020/02/22","book":{"title":"Book 1","author":"Author 1"},"person":{"name":"Nadia","age":12,"id":472,"parent_permission":false,"class":"Student"}},{"date":"2023/05/05","book":{"title":"Book 2","author":"Author 2"},"person":{"name":"Silvina","age":55,"specialization":"Phisics","parent_permission":true,"id":908,"class":"Teacher"}},{"date":"2023/05/21","book":{"title":"Book 1","author":"Author 1"},"person":{"name":"PersonExample","age":44,"id":325,"parent_permission":true,"class":"Student"}}]
